pymd4c.libs/libmd4c-93c4b1bd.so.0.4.8
pymd4c.libs/libmd4c-html-d979db9e.so.0.4.8
pymd4c-1.3.0.dist-info/LICENSE.md
pymd4c-1.3.0.dist-info/WHEEL
pymd4c-1.3.0.dist-info/top_level.txt
pymd4c-1.3.0.dist-info/RECORD
pymd4c-1.3.0.dist-info/METADATA
md4c/_enum_consts.cpython-39-s390x-linux-gnu.so
md4c/enums.py
md4c/parser.py
md4c/__init__.py
md4c/_md4c.cpython-39-s390x-linux-gnu.so
md4c/domparser/domparser.py
md4c/domparser/ast.py
md4c/domparser/__init__.py
