Metadata-Version: 2.1
Name: pymd4c
Version: 1.3.0
Summary: Python bindings for MD4C
Home-page: https://github.com/dominickpastore/pymd4c
Author: Dominick C. Pastore
Author-email: dominickpastore@dcpx.org
Classifier: Programming Language :: C
Classifier: Programming Language :: Python :: 3
Classifier: License :: OSI Approved :: MIT License
Classifier: Topic :: Text Processing :: Markup
Requires-Python: >=3.6
License-File: LICENSE.md
Provides-Extra: test
Requires-Dist: pytest ; extra == 'test'
Requires-Dist: flake8 ; extra == 'test'
